<?xml version="1.0" encoding="utf-8" ?><dwsync><file name=".DS_Store" server="designannexe.com/maps.ponabana.com/html/" local="3462994308" remote="7791777616" Dst="-1" /><file name="charmap.php" server="designannexe.com/maps.ponabana.com/html/" local="3479410818" remote="-4611698556235081904" Dst="-1" /><file name="charmap-compat.php" server="designannexe.com/maps.ponabana.com/html/" local="3462994388" remote="-4611698556235081844" Dst="-1" /><file name="config.json" server="designannexe.com/maps.ponabana.com/html/" local="3479416954" remote="-4611698556235081844" Dst="-1" /><file name="entypo-fontello.eot" server="designannexe.com/maps.ponabana.com/html/" local="3479416954" remote="-4611698556235081844" Dst="-1" /><file name="entypo-fontello.ttf" server="designannexe.com/maps.ponabana.com/html/" local="3479416954" remote="-4611698556235081844" Dst="-1" /><file name="entypo-fontello.woff" server="designannexe.com/maps.ponabana.com/html/" local="3479416954" remote="-4611698556235081844" Dst="-1" /><file name="entypo-fontello.svg" server="designannexe.com/maps.ponabana.com/html/" local="3479416954" remote="-4611698556235081844" Dst="-1" /></dwsync>